[{"timestamp":"2022-11-04T00:30:22.284Z","count":0,"uniques":0},{"timestamp":"2022-11-05T00:30:03.364Z","count":0,"uniques":0},{"timestamp":"2022-11-06T00:28:04.593Z","count":0,"uniques":0},{"timestamp":"2022-11-07T00:26:30.080Z","count":0,"uniques":0},{"timestamp":"2022-11-08T00:27:32.015Z","count":0,"uniques":0},{"timestamp":"2022-11-09T00:28:05.331Z","count":0,"uniques":0},{"timestamp":"2022-11-10T00:29:01.704Z","count":0,"uniques":0},{"timestamp":"2022-11-11T00:31:15.557Z","count":0,"uniques":0}]
