[{"timestamp":"2021-09-04T01:08:28.446Z","count":0,"uniques":0},{"timestamp":"2021-09-05T01:11:06.511Z","count":0,"uniques":0},{"timestamp":"2021-09-06T01:14:28.177Z","count":0,"uniques":0},{"timestamp":"2021-09-07T01:05:54.689Z","count":0,"uniques":0},{"timestamp":"2021-09-08T01:06:54.726Z","count":0,"uniques":0},{"timestamp":"2021-09-09T01:11:37.031Z","count":0,"uniques":0},{"timestamp":"2021-09-10T01:12:48.190Z","count":0,"uniques":0},{"timestamp":"2021-09-11T01:06:47.511Z","count":0,"uniques":0}]
