[{"timestamp":"2023-05-12T00:22:15.992Z","count":0,"uniques":0},{"timestamp":"2023-05-13T00:21:51.456Z","count":0,"uniques":0},{"timestamp":"2023-05-14T00:25:24.519Z","count":0,"uniques":0},{"timestamp":"2023-05-15T00:24:20.619Z","count":0,"uniques":0},{"timestamp":"2023-05-16T00:00:00.000Z","count":1,"uniques":1},{"timestamp":"2023-05-17T00:25:50.863Z","count":0,"uniques":0},{"timestamp":"2023-05-18T00:23:10.459Z","count":0,"uniques":0},{"timestamp":"2023-05-19T00:23:14.376Z","count":0,"uniques":0}]
