[{"timestamp":"2024-07-02T00:25:32.370Z","count":0,"uniques":0},{"timestamp":"2024-07-03T00:25:32.466Z","count":0,"uniques":0},{"timestamp":"2024-07-04T00:25:11.256Z","count":0,"uniques":0},{"timestamp":"2024-07-05T00:25:18.789Z","count":0,"uniques":0},{"timestamp":"2024-07-06T00:24:37.848Z","count":0,"uniques":0},{"timestamp":"2024-07-07T00:28:13.687Z","count":0,"uniques":0},{"timestamp":"2024-07-08T00:26:54.305Z","count":0,"uniques":0},{"timestamp":"2024-07-09T00:25:36.052Z","count":0,"uniques":0}]
