[{"timestamp":"2024-02-18T00:24:46.396Z","count":0,"uniques":0},{"timestamp":"2024-02-19T00:23:48.770Z","count":0,"uniques":0},{"timestamp":"2024-02-20T00:22:40.794Z","count":0,"uniques":0},{"timestamp":"2024-02-21T00:23:03.631Z","count":0,"uniques":0},{"timestamp":"2024-02-22T00:22:53.136Z","count":0,"uniques":0},{"timestamp":"2024-02-23T00:22:53.997Z","count":0,"uniques":0},{"timestamp":"2024-02-24T00:21:35.614Z","count":0,"uniques":0},{"timestamp":"2024-02-25T00:24:43.625Z","count":0,"uniques":0}]
