[{"timestamp":"2025-01-16T00:28:22.939Z","count":0,"uniques":0},{"timestamp":"2025-01-17T00:00:00.000Z","count":1,"uniques":1},{"timestamp":"2025-01-18T00:27:03.424Z","count":0,"uniques":0},{"timestamp":"2025-01-19T00:00:00.000Z","count":1,"uniques":1},{"timestamp":"2025-01-20T00:00:00.000Z","count":4,"uniques":2},{"timestamp":"2025-01-21T00:28:06.480Z","count":0,"uniques":0},{"timestamp":"2025-01-22T00:28:47.314Z","count":0,"uniques":0},{"timestamp":"2025-01-23T00:28:18.968Z","count":0,"uniques":0}]
