[{"timestamp":"2022-02-08T01:17:32.474Z","count":0,"uniques":0},{"timestamp":"2022-02-09T01:20:25.390Z","count":0,"uniques":0},{"timestamp":"2022-02-10T01:16:35.425Z","count":0,"uniques":0},{"timestamp":"2022-02-11T01:20:11.901Z","count":0,"uniques":0},{"timestamp":"2022-02-12T01:21:08.338Z","count":0,"uniques":0},{"timestamp":"2022-02-13T01:21:26.596Z","count":0,"uniques":0},{"timestamp":"2022-02-14T01:13:42.176Z","count":0,"uniques":0},{"timestamp":"2022-02-15T01:25:15.228Z","count":0,"uniques":0}]
