[{"timestamp":"2024-02-11T00:25:47.342Z","count":0,"uniques":0},{"timestamp":"2024-02-12T00:24:05.872Z","count":0,"uniques":0},{"timestamp":"2024-02-13T00:23:42.349Z","count":0,"uniques":0},{"timestamp":"2024-02-14T00:23:13.986Z","count":0,"uniques":0},{"timestamp":"2024-02-15T00:23:22.498Z","count":0,"uniques":0},{"timestamp":"2024-02-16T00:22:55.846Z","count":0,"uniques":0},{"timestamp":"2024-02-17T00:23:08.957Z","count":0,"uniques":0},{"timestamp":"2024-02-18T00:25:06.217Z","count":0,"uniques":0}]
