[{"timestamp":"2024-11-27T00:32:29.377Z","count":0,"uniques":0},{"timestamp":"2024-11-28T00:32:30.991Z","count":0,"uniques":0},{"timestamp":"2024-11-29T00:32:30.021Z","count":0,"uniques":0},{"timestamp":"2024-11-30T00:31:29.113Z","count":0,"uniques":0},{"timestamp":"2024-12-01T00:39:04.635Z","count":0,"uniques":0},{"timestamp":"2024-12-02T00:34:19.345Z","count":0,"uniques":0},{"timestamp":"2024-12-03T00:33:54.017Z","count":0,"uniques":0},{"timestamp":"2024-12-04T00:33:30.264Z","count":0,"uniques":0}]
