[{"timestamp":"2023-07-23T00:27:07.795Z","count":0,"uniques":0},{"timestamp":"2023-07-24T00:25:39.740Z","count":0,"uniques":0},{"timestamp":"2023-07-25T00:00:00.000Z","count":1,"uniques":1},{"timestamp":"2023-07-26T00:00:00.000Z","count":1,"uniques":1},{"timestamp":"2023-07-27T00:22:59.960Z","count":0,"uniques":0},{"timestamp":"2023-07-28T00:23:35.785Z","count":0,"uniques":0},{"timestamp":"2023-07-29T00:23:10.427Z","count":0,"uniques":0},{"timestamp":"2023-07-30T00:26:12.040Z","count":0,"uniques":0}]
